betterface/__init__.py
betterface/__main__.py
betterface/interface.py
better_face-1.0.2.dist-info/METADATA
better_face-1.0.2.dist-info/WHEEL
better_face-1.0.2.dist-info/entry_points.txt
better_face-1.0.2.dist-info/top_level.txt
better_face-1.0.2.dist-info/RECORD
