Metadata-Version: 2.1
Name: better-face
Version: 1.0.2
Summary: General image  and face restoration
Home-page: https://github.com/leonelhs
Author: Leonel Hernandez
Author-email: leonelhs@gmail.com
License: MIT License
Requires-Python: >=3.6
Requires-Dist: gradio (==3.35.2)
Requires-Dist: torch (>=2.0.1)
Requires-Dist: basicsr (>=1.4.2)
Requires-Dist: facexlib (>=0.3.0)
Requires-Dist: gfpgan (>=1.3.8)
Requires-Dist: realesrgan (>=0.3.0)
Requires-Dist: numpy
Requires-Dist: opencv-python
Requires-Dist: torchvision
Requires-Dist: scipy
Requires-Dist: tqdm
Requires-Dist: lmdb
Requires-Dist: pyyaml
Requires-Dist: yapf
